ckanext_logs-1.0.1-py3.10-nspkg.pth
ckanext/logs/__init__.py
ckanext/logs/config.py
ckanext/logs/data_source.py
ckanext/logs/formatters.py
ckanext/logs/helpers.py
ckanext/logs/plugin.py
ckanext/logs/table.py
ckanext/logs/views.py
ckanext/logs/templates/header.html
ckanext/logs/templates/logs/dashboard.html
ckanext/logs/templates/logs/formatters/dialog_modal.html
ckanext_logs-1.0.1.dist-info/licenses/LICENSE
ckanext_logs-1.0.1.dist-info/METADATA
ckanext_logs-1.0.1.dist-info/WHEEL
ckanext_logs-1.0.1.dist-info/entry_points.txt
ckanext_logs-1.0.1.dist-info/namespace_packages.txt
ckanext_logs-1.0.1.dist-info/top_level.txt
ckanext_logs-1.0.1.dist-info/RECORD
