Metadata-Version: 2.4
Name: ckanext-logs
Version: 1.0.1
Summary: Log file viewer
Author-email: Oleksandr Cherniavskiy <mutantsan@gmail.com>
License: AGPL
Project-URL: Homepage, https://github.com/DataShades/ckanext-logs
Keywords: CKAN
Classifier: Development Status :: 4 - Beta
Classifier: License :: OSI Approved :: GNU Affero General Public License v3 or later (AGPLv3+)
Classifier: Programming Language :: Python :: 3.10
Classifier: Programming Language :: Python :: 3.11
Classifier: Programming Language :: Python :: 3.12
License-File: LICENSE
Requires-Dist: ckanext-tables<2.0.0,>=1.5.1
Dynamic: license-file
